kiss/__init__.py
kiss/constants.py
pykiss-0.2.1.dist-info/METADATA
pykiss-0.2.1.dist-info/WHEEL
pykiss-0.2.1.dist-info/top_level.txt
pykiss-0.2.1.dist-info/RECORD
