Metadata-Version: 2.1
Name: pykiss
Version: 0.2.1
Summary: Simple serial KISS library
Home-page: https://github.com/jlangvand/pykiss
Author: Orbit NTNU
Author-email: cto@orbitntnu.com
License: UNKNOWN
Project-URL: Orbit NTNU, https://orbitntnu.com
Platform: UNKNOWN
Classifier: Development Status :: 3 - Alpha
Classifier: Environment :: Console
Classifier: Intended Audience :: Developers
Classifier: Natural Language :: English
Classifier: Topic :: Communications :: Ham Radio
Classifier: Programming Language :: Python :: 3
Classifier: License :: OSI Approved :: GNU General Public License v3 (GPLv3)
Classifier: Operating System :: POSIX :: Linux
Requires-Python: >=3.6
Requires-Dist: pyserial
